shtab/__init__.py
shtab/__main__.py
shtab/_dist_ver.py
shtab/main.py
shtab/py.typed
shtab-1.7.1.dist-info/LICENCE
shtab-1.7.1.dist-info/METADATA
shtab-1.7.1.dist-info/WHEEL
shtab-1.7.1.dist-info/entry_points.txt
shtab-1.7.1.dist-info/top_level.txt
shtab-1.7.1.dist-info/RECORD
